gmlp/__init__.py
gmlp/core/__init__.py
gmlp/core/evolution.py
gmlp/core/fitness.py
gmlp/core/mutations.py
gmlp/core/selection.py
gmlp-0.2.dist-info/LICENSE.txt
gmlp-0.2.dist-info/METADATA
gmlp-0.2.dist-info/WHEEL
gmlp-0.2.dist-info/top_level.txt
gmlp-0.2.dist-info/RECORD
