Metadata-Version: 2.1
Name: gmlp
Version: 0.2
Summary: Genetic Algorithm for Python
Home-page: https://github.com/CoderWeird/gmlp
Author: Drew Montooth
Author-email: drewmontooth@gmail.com
License: UNKNOWN
Platform: UNKNOWN
Classifier: Development Status :: 3 - Alpha
Classifier: Intended Audience :: Developers
Classifier: Topic :: Scientific/Engineering :: Artificial Intelligence
Classifier: License :: OSI Approved :: MIT License
Classifier: Programming Language :: Python :: 2.7
Requires-Python: >=2.7
Requires-Dist: pygame
